es_clarify/__init__.py
es_clarify/decorator.py
es_clarify-0.0.1.dist-info/LICENSE
es_clarify-0.0.1.dist-info/METADATA
es_clarify-0.0.1.dist-info/WHEEL
es_clarify-0.0.1.dist-info/top_level.txt
es_clarify-0.0.1.dist-info/RECORD
